google_search_api/__init__.py
google_search_api/cli.py
google_search_api/google_search_api.py
google_opensearch_api-1.0.13.dist-info/LICENSE
google_opensearch_api-1.0.13.dist-info/METADATA
google_opensearch_api-1.0.13.dist-info/WHEEL
google_opensearch_api-1.0.13.dist-info/entry_points.txt
google_opensearch_api-1.0.13.dist-info/top_level.txt
google_opensearch_api-1.0.13.dist-info/RECORD
